Workbook

Sheet Projections
A1: Details | B1: Year 0 | C1: Year 1 | D1: Year 2 | E1: Year 3 | F1: Year 4 | G1: Year 5 | H1: Year 6 | I1: Year 7 | J1: Year 8 | K1: Year 9 | L1: Year 10
A2: Projected Revenue | C2: ='Revenue Streams'!B7 -> 500000 | D2: ='Revenue Streams'!C7 -> 700000 | E2: ='Revenue Streams'!D7 -> 900000 | F2: ='Revenue Streams'!E7 -> 1035000 | G2: ='Revenue Streams'!F7 -> 1196275 | H2: ='Revenue Streams'!G7 -> 1384261 | I2: ='Revenue Streams'!H7 -> 1602073 | J2: ='Revenue Streams'!I7 -> 1857797 | ... L2: ='Revenue Streams'!K7 -> 2512867
A3: Initial Investment | B3: ='Startup Costs'!B7 -> 53280
A4: Operational Costs | C4: ='Operational Costs'!B8 -> 808000 | D4: ='Operational Costs'!C8 -> 887800 | E4: ='Operational Costs'!D8 -> 975780 | F4: ='Operational Costs'!E8 -> 1072358 | G4: ='Operational Costs'!F8 -> 1178595 | H4: ='Operational Costs'!G8 -> 1295453 | I4: ='Operational Costs'!H8 -> 1423999 | J4: ='Operational Costs'!I8 -> 1565398 | ... L4: ='Operational Costs'!K8 -> 1892031
A5: Profit/Loss | B5: =B2-B3-B4 -> -53280 | C5: =C2-C3-C4 -> -308000 | D5: =D2-D3-D4 -> -187800 | E5: =E2-E3-E4 -> -75780 | F5: =F2-F3-F4 -> -37358 | G5: =G2-G3-G4 -> 17680 | H5: =H2-H3-H4 -> 88808 | I5: =I2-I3-I4 -> 178074 | ... L5: =L2-L3-L4 -> 620836
A6: Cumulative P/L | B6: -53280 | C6: =B6+C5 -> -361280 | D6: =C6+D5 -> -549080 | E6: =D6+E5 -> -624860 | F6: =E6+F5 -> -662218 | G6: =F6+G5 -> -644538 | H6: =G6+H5 -> -555730 | I6: =H6+I5 -> -377656 | J6: =I6+J5 -> -85257 | ... L6: =K6+L5 -> 974008
A8: Net Present Value | B8: ='Net Present Value'!C13 -> 130229.71
A10: Original stake for the same effort | B10: =B3/B8 -> 0.40912322
A12: Negotiate not more than | B12: 0.15

Sheet Startup Costs
A1: Startup Expenses | B1: Cost
A2: Raspberry Pi or Arduino | B2: 15000
A3: Sensors | B3: 20000
A4: Wires and breadboard | B4: 1280
A5: Initial Software Development | B5: 12000
A6: Preliminary Marketing & Research | B6: 5000
A7: Total Startup Costs | B7: =SUM(B2:B6) -> 53280
A10: Rationale
A11: Hardware Costs
A12: Raspberry Pi or Arduino: $50/unit
A13: All mentioned sensors (Camera, GPS, Accelerometer, etc.): $200/unit
A14: Wires and Breadboard: $30/unit
A15: Software & Development Costs
A16: Landing website development and maintenance: $3,000
A17: AI models and software solution development: $20,000
A18: Marketing Costs
A19: Google ads, Instagram promotions: $10,000 initial campaign
A20: Outreach to potential customers for interviews: $2,000
A21: Miscellaneous Costs
... A26: Total Startup Cost: ~$53,280

Sheet Revenue Streams
A1: Revenue Streams | B1: Year 1 | C1: Year 2 | D1: Year 3 | E1: Year 4 | F1: Year 5 | G1: Year 6 | H1: Year 7 | I1: Year 8 | J1: Year 9 | K1: Year 10
A2: Government Contracts | B2: 100000 | C2: 150000 | D2: 200000 | E2: 230000 | F2: 265000 | G2: 305000 | H2: 351000 | I2: 403000 | J2: 463000 | K2: 532000
A3: AI Company Contracts | B3: 60000 | C3: 90000 | D3: 120000 | E3: 138000 | F3: 159000 | G3: 183000 | H3: 210000 | I3: 241000 | J3: 277000 | K3: 318000
A4: Licensing Deals & API Tokens | B4: 70000 | C4: 90000 | D4: 105000 | E4: 120500 | F4: 138500 | G4: 158500 | H4: 181500 | I4: 208000 | J4: 238500 | K4: 273000
A5: Advertisement Revenue | B5: 6000 | C5: 12000 | D5: 18000 | E5: 25200 | F5: 35280 | G5: 49392 | H5: 69150 | I5: 96810 | J5: 135532 | K5: 189743
A6: Subscription Models & Tiered Data Packages | B6: 264000 | C6: 358000 | D6: 457000 | E6: 521300 | F6: 598495 | G6: 688369 | H6: 790423 | I6: 908987 | J6: 1045335 | K6: 1200124
A7: Total | B7: =SUM(B2:B6) -> 500000 | C7: =SUM(C2:C6) -> 700000 | D7: =SUM(D2:D6) -> 900000 | E7: =SUM(E2:E6) -> 1035000 | F7: =SUM(F2:F6) -> 1196275 | G7: =SUM(G2:G6) -> 1384261 | H7: =SUM(H2:H6) -> 1602073 | I7: =SUM(I2:I6) -> 1857797 | ... K7: =SUM(K2:K6) -> 2512867
A9: Rationale
A10: 1. Government Contracts: | D10: Year 1 to Year 2 saw a 50% increase ($50,000 increase on $100,000).
A11: - 2 contracts at $50,000 each: | B11: 100000 | D11: Year 2 to Year 3 saw a 33.33% increase ($50,000 increase on $150,000).
D12: Year 3 to Year 4 saw a 15% increase ($30,000 increase on $200,000).
A13: 2. AI Company Contracts: | D13: From Year 4 onwards, there's an approximately consistent growth of 15% annually.
A14: - 3 contracts at $20,000 each: | B14: 60000
A16: 3. Licensing Deals & API Tokens:
A17: - Estimating an average of 5 licenses at $10,000 each: | B17: 50000
A18: - Estimating API tokens sale to 100 users at $200 each: | B18: 20000
A20: 4. Advertisement Revenue:
A21: - Estimating a modest monthly revenue of $500 for ads on the platform (annually): | B21: 6000
A22: - Sponsored content: Assuming 5 posts at $1,000 each: | B22: 5000
A24: 5. Subscription Models & Tiered Data Packages (as detailed above):
A25: - Data Access Subscriptions (Basic): 50 users at $500/month (annually): | B25: 300000
A26: - Data Access Subscriptions (Premium): 20 users at $2,000/month (annually): | B26: 480000

Sheet Operational Costs
A1: Operational Cost Components | B1: Year 1 | C1: Year 2 | D1: Year 3 | E1: Year 4 | F1: Year 5 | G1: Year 6 | H1: Year 7 | I1: Year 8 | J1: Year 9 | K1: Year 10
A2: Hardware & Equipment Maintenance | B2: 303000 | C2: 333300 | D2: 366630 | E2: 403293 | F2: 443622 | G2: 487984 | H2: 536783 | I2: 590461 | J2: 649507 | K2: 714458
A3: Software & Development | B3: 65000 | C3: 70500 | D3: 76750 | E3: 83425 | F3: 90768 | G3: 98845 | H3: 107729 | I3: 117502 | J3: 128252 | K3: 140077
A4: Marketing & Sales | B4: 130000 | C4: 143000 | D4: 157300 | E4: 173030 | F4: 190333 | G4: 209366 | H4: 230303 | I4: 253333 | J4: 278666 | K4: 306533
A5: Administrative & Overhead | B5: 235000 | C5: 258500 | D5: 284350 | E5: 312785 | F5: 344064 | G5: 378470 | H5: 416317 | I5: 457949 | J5: 503744 | K5: 554118
A6: Licensing, Legal & Compliance | B6: 35000 | C6: 38500 | D6: 42350 | E6: 46585 | F6: 51244 | G6: 56368 | H6: 62005 | I6: 68205 | J6: 75026 | K6: 82528
A7: Customer Support & Training | B7: 40000 | C7: 44000 | D7: 48400 | E7: 53240 | F7: 58564 | G7: 64420 | H7: 70862 | I7: 77948 | J7: 85743 | K7: 94317
A8: Total | B8: =SUM(B2:B7) -> 808000 | C8: =SUM(C2:C7) -> 887800 | D8: =SUM(D2:D7) -> 975780 | E8: =SUM(E2:E7) -> 1072358 | F8: =SUM(F2:F7) -> 1178595 | G8: =SUM(G2:G7) -> 1295453 | H8: =SUM(H2:H7) -> 1423999 | I8: =SUM(I2:I7) -> 1565398 | ... K8: =SUM(K2:K7) -> 1892031
A11: Absolutely, let's detail out the operational costs for "Easy Transport" in its first year.
A12: 1. Hardware & Equipment:
A13: - Device Production:
A14: - Let's say you manufacture 1,000 devices in the first year.
A15: - Assuming each device's cost (including sensors, Raspberry Pi or Arduino, wires, and other materials) averages at $300: 1,000 x $300 = $300,000
A16: - Maintenance & Repairs:
A17: - Assuming a 10% maintenance rate, at an average of $30 per device: 100 x $30 = $3,000
A19: 2. Software & Development:
A20: - Platform Maintenance & Hosting: $10,000 (includes server costs, security measures, and updates)
A21: - Software Development & Updates: $50,000 (This includes salaries or fees for developers, testing, and deployment.)
A22: - Cloud Storage: Based on the amount of data and the need for quick access, let's budget $5,000 for the first year.
A24: 3. Marketing & Sales:
... A41: - Training Programs & Workshops: $10,000 (Both for internal teams and external clients.)

Sheet Net Present Value
A1: Year | B1: Net Cash Flow (Revenue - Operational Costs) | C1: NPV (using 10% discount rate)
A2: 0 (Startup Costs) | B2: =Projections!B5 -> -53280 | C2: =NPV($B$15,B2) -> -48436.364
A3: 1 | B3: =Projections!C5 -> -308000 | C3: =NPV($B$15,B3) -> -280000
A4: 2 | B4: =Projections!D5 -> -187800 | C4: =NPV($B$15,B4) -> -170727.27
A5: 3 | B5: =Projections!E5 -> -75780 | C5: =NPV($B$15,B5) -> -68890.909
A6: 4 | B6: =Projections!F5 -> -37358 | C6: =NPV($B$15,B6) -> -33961.818
A7: 5 | B7: =Projections!G5 -> 17680 | C7: =NPV($B$15,B7) -> 16072.727
A8: 6 | B8: =Projections!H5 -> 88808 | C8: =NPV($B$15,B8) -> 80734.545
A9: 7 | B9: =Projections!I5 -> 178074 | C9: =NPV($B$15,B9) -> 161885.45
A10: 8 | B10: =Projections!J5 -> 292399 | C10: =NPV($B$15,B10) -> 265817.27
A11: 9 | B11: =Projections!K5 -> 438429 | C11: =NPV($B$15,B11) -> 398571.82
A12: 10 | B12: =Projections!L5 -> 620836 | C12: =NPV($B$15,B12) -> 564396.36
A13: Total NPV over 10 years | B13: - | C13: {=NPV(B15, B2:B12)} -> 130229.71
A15: Discounting Rate | B15: 0.1
